masking_sensitive_data/__init__.py
masking_sensitive_data/config.py
masking_sensitive_data/adapters/__init__.py
masking_sensitive_data/adapters/requests.py
masking_sensitive_data/adapters/zipkin.py
masking_sensitive_data/logic/__init__.py
masking_sensitive_data/logic/masking.py
masking_sensitive_data-0.1.3.dist-info/LICENSE
masking_sensitive_data-0.1.3.dist-info/METADATA
masking_sensitive_data-0.1.3.dist-info/WHEEL
masking_sensitive_data-0.1.3.dist-info/top_level.txt
masking_sensitive_data-0.1.3.dist-info/RECORD
