Metadata-Version: 2.1
Name: masking-sensitive-data
Version: 0.1.3
Summary: Package for capturing and masking sensitive data
Home-page: UNKNOWN
Author: InPlat
License: UNKNOWN
Platform: UNKNOWN
Classifier: Programming Language :: Python
Classifier: Programming Language :: Python :: 3
Classifier: Programming Language :: Python :: 3 :: Only
Classifier: Programming Language :: Python :: 3.7
Classifier: Programming Language :: Python :: 3.8
Classifier: Intended Audience :: Developers
Classifier: Intended Audience :: Information Technology
Classifier: Intended Audience :: System Administrators
Classifier: Operating System :: Unix
Classifier: Operating System :: POSIX :: Linux
Classifier: Topic :: Software Development :: Libraries :: Python Modules
Classifier: Topic :: Internet
Requires-Python: >=3.7
Provides-Extra: ipapp
Requires-Dist: ipapp[rabbitmq] ; extra == 'ipapp'
